PBHBeta/BfM.py
PBHBeta/BfN.py
PBHBeta/BfS.py
PBHBeta/KfN.py
PBHBeta/KfS.py
PBHBeta/PfM.py
PBHBeta/PfR.py
PBHBeta/PfS.py
PBHBeta/__init__.py
PBHBeta/constants.py
PBHBeta/constraints.py
PBHBeta/functions.py
PBHBeta-1.0.5.dist-info/LICENSE
PBHBeta-1.0.5.dist-info/METADATA
PBHBeta-1.0.5.dist-info/WHEEL
PBHBeta-1.0.5.dist-info/top_level.txt
PBHBeta-1.0.5.dist-info/RECORD
