Metadata-Version: 2.1
Name: PBHBeta
Version: 1.0.5
Summary: PBHBeta, a code to explore the constraints on PBH abundances and power spectrum.
Home-page: https://github.com/TadeoDGAguilar/PBHBeta
Author: ['Tadeo D. GA', 'Luis E. PA']
Maintainer: Tadeo D. Gómez Aguilar
Maintainer-email: tadeo.daguilar@gmail.com
License: GNU GPL
License-File: LICENSE
Requires-Dist: matplotlib
Requires-Dist: numpy
Requires-Dist: scipy
